pchealthstream2py/__init__.py
pchealthstream2py/pchealth.py
pchealthstream2py-0.0.2.dist-info/LICENSE
pchealthstream2py-0.0.2.dist-info/METADATA
pchealthstream2py-0.0.2.dist-info/WHEEL
pchealthstream2py-0.0.2.dist-info/top_level.txt
pchealthstream2py-0.0.2.dist-info/RECORD
