Metadata-Version: 2.1
Name: pchealthstream2py
Version: 0.0.2
Summary: stream2py interface to pc health
Home-page: https://github.com/i2mint/pchealthstream2py
Author: OtoSense
License: apache-2.0
Platform: any
